<annotation>
	<folder></folder>
	<filename>IMG_1424_JPG.rf.562df617e02125613af1b636bd844bea.jpg</filename>
	<path>IMG_1424_JPG.rf.562df617e02125613af1b636bd844bea.jpg</path>
	<source>
		<database>roboflow.com</database>
	</source>
	<size>
		<width>640</width>
		<height>640</height>
		<depth>3</depth>
	</size>
	<segmented>0</segmented>
	<object>
		<name>charette</name>
		<pose>Unspecified</pose>
		<truncated>0</truncated>
		<difficult>0</difficult>
		<occluded>0</occluded>
		<bndbox>
			<xmin>2</xmin>
			<xmax>360</xmax>
			<ymin>216</ymin>
			<ymax>437</ymax>
		</bndbox>
		<polygon>
			<x1>308.125</x1>
			<y1>215.277061</y1>
			<x2>1.292029</x2>
			<y2>238.306418</y2>
			<x3>39.680361</x3>
			<y3>436.145564</y3>
			<x4>209.374999</x4>
			<y4>410.52835</y4>
			<x5>358.750001</x5>
			<y5>389.66817</y5>
			<x6>345.625</x6>
			<y6>228.627576</y6>
			<x7>308.125</x7>
			<y7>215.277061</y7>
		</polygon>
	</object>
	<object>
		<name>particulier</name>
		<pose>Unspecified</pose>
		<truncated>0</truncated>
		<difficult>0</difficult>
		<occluded>0</occluded>
		<bndbox>
			<xmin>385</xmin>
			<xmax>641</xmax>
			<ymin>225</ymin>
			<ymax>381</ymax>
		</bndbox>
		<polygon>
			<x1>639.374999</x1>
			<y1>360.463918</y1>
			<x2>640</x2>
			<y2>224.455541</y2>
			<x3>484.375</x3>
			<y3>233.634019</y3>
			<x4>394.375</x4>
			<y4>282.029638</y4>
			<x5>383.75</x5>
			<y5>307.896264</y5>
			<x6>383.75</x6>
			<y6>339.603738</y6>
			<x7>400.625001</x7>
			<y7>360.463918</y7>
			<x8>456.875001</x8>
			<y8>380.489692</y8>
			<x9>639.374999</x9>
			<y9>360.463918</y9>
		</polygon>
	</object>
</annotation>
