<annotation>
	<folder></folder>
	<filename>IMG_0976_jpg.rf.b5d208433f64a097d4323fe73406daae.jpg</filename>
	<path>IMG_0976_jpg.rf.b5d208433f64a097d4323fe73406daae.jpg</path>
	<source>
		<database>roboflow.com</database>
	</source>
	<size>
		<width>640</width>
		<height>640</height>
		<depth>3</depth>
	</size>
	<segmented>0</segmented>
	<object>
		<name>taxi</name>
		<pose>Unspecified</pose>
		<truncated>0</truncated>
		<difficult>0</difficult>
		<occluded>0</occluded>
		<bndbox>
			<xmin>1</xmin>
			<xmax>149</xmax>
			<ymin>189</ymin>
			<ymax>440</ymax>
		</bndbox>
		<polygon>
			<x1>0</x1>
			<y1>434.375</y1>
			<x2>2.5</x2>
			<y2>436.25</y2>
			<x3>5</x3>
			<y3>436.875</y3>
			<x4>3.333333</x4>
			<y4>438.125</y4>
			<x5>4.166667</x5>
			<y5>438.75</y5>
			<x6>6.666667</x6>
			<y6>438.125</y6>
			<x7>9.166667</x7>
			<y7>436.25</y7>
			<x8>10.833333</x8>
			<y8>436.25</y8>
			<x9>13.333333</x9>
			<y9>434.375</y9>
			<x10>13.333333</x10>
			<y10>433.125</y10>
			<x11>18.333333</x11>
			<y11>429.375</y11>
			<x12>18.333333</x12>
			<y12>428.125</y12>
			<x13>22.5</x13>
			<y13>425</y13>
			<x14>24.166667</x14>
			<y14>425</y14>
			<x15>26.666667</x15>
			<y15>423.125</y15>
			<x16>26.666667</x16>
			<y16>421.875</y16>
			<x17>28.333333</x17>
			<y17>420.625</y17>
			<x18>30</x18>
			<y18>416.875</y18>
			<x19>38.333333</x19>
			<y19>410.625</y19>
			<x20>38.333333</x20>
			<y20>409.375</y20>
			<x21>41.666667</x21>
			<y21>406.875</y21>
			<x22>41.666667</x22>
			<y22>401.875</y22>
			<x23>42.5</x23>
			<y23>401.25</y23>
			<x24>45.833333</x24>
			<y24>401.25</y24>
			<x25>53.333333</x25>
			<y25>395.625</y25>
			<x26>53.333333</x26>
			<y26>391.875</y26>
			<x27>55.833333</x27>
			<y27>390</y27>
			<x28>58.333333</x28>
			<y28>389.375</y28>
			<x29>58.333333</x29>
			<y29>386.875</y29>
			<x30>59.166667</x30>
			<y30>386.25</y30>
			<x31>62.5</x31>
			<y31>386.25</y31>
			<x32>65</x32>
			<y32>384.375</y32>
			<x33>65</x33>
			<y33>383.125</y33>
			<x34>70</x34>
			<y34>379.375</y34>
			<x35>70</x35>
			<y35>378.125</y35>
			<x36>75</x36>
			<y36>374.375</y36>
			<x37>75</x37>
			<y37>371.875</y37>
			<x38>77.5</x38>
			<y38>371.25</y38>
			<x39>80</x39>
			<y39>369.375</y39>
			<x40>80</x40>
			<y40>368.125</y40>
			<x41>81.666667</x41>
			<y41>366.875</y41>
			<x42>81.666667</x42>
			<y42>363.125</y42>
			<x43>82.5</x43>
			<y43>362.5</y43>
			<x44>84.166667</x44>
			<y44>363.75</y44>
			<x45>85.833333</x45>
			<y45>361.25</y45>
			<x46>89.166667</x46>
			<y46>361.25</y46>
			<x47>90.833333</x47>
			<y47>360</y47>
			<x48>91.666667</x48>
			<y48>361.875</y48>
			<x49>90</x49>
			<y49>363.125</y49>
			<x50>90</x50>
			<y50>364.375</y50>
			<x51>86.666667</x51>
			<y51>366.875</y51>
			<x52>89.166667</x52>
			<y52>368.75</y52>
			<x53>104.166667</x53>
			<y53>368.75</y53>
			<x54>105.833333</x54>
			<y54>367.5</y54>
			<x55>109.166667</x55>
			<y55>367.5</y55>
			<x56>116.666667</x56>
			<y56>361.875</y56>
			<x57>116.666667</x57>
			<y57>360.625</y57>
			<x58>120</x58>
			<y58>358.125</y58>
			<x59>120</x59>
			<y59>354.375</y59>
			<x60>123.333333</x60>
			<y60>350.625</y60>
			<x61>123.333333</x61>
			<y61>345.625</y61>
			<x62>125</x62>
			<y62>344.375</y62>
			<x63>125</x63>
			<y63>339.375</y63>
			<x64>126.666667</x64>
			<y64>338.125</y64>
			<x65>126.666667</x65>
			<y65>325.625</y65>
			<x66>128.333333</x66>
			<y66>324.375</y66>
			<x67>128.333333</x67>
			<y67>316.875</y67>
			<x68>130</x68>
			<y68>315.625</y68>
			<x69>130.833333</x69>
			<y69>313.75</y69>
			<x70>134.166667</x70>
			<y70>313.75</y70>
			<x71>135</x71>
			<y71>313.125</y71>
			<x72>135</x72>
			<y72>308.125</y72>
			<x73>138.333333</x73>
			<y73>304.375</y73>
			<x74>138.333333</x74>
			<y74>301.875</y74>
			<x75>140</x75>
			<y75>300.625</y75>
			<x76>140</x76>
			<y76>296.875</y76>
			<x77>143.333333</x77>
			<y77>294.375</y77>
			<x78>143.333333</x78>
			<y78>290.625</y78>
			<x79>145</x79>
			<y79>289.375</y79>
			<x80>145</x80>
			<y80>286.875</y80>
			<x81>146.666667</x81>
			<y81>285.625</y81>
			<x82>146.666667</x82>
			<y82>280.625</y82>
			<x83>148.333333</x83>
			<y83>279.375</y83>
			<x84>148.333333</x84>
			<y84>276.875</y84>
			<x85>146.666667</x85>
			<y85>275.625</y85>
			<x86>146.666667</x86>
			<y86>273.125</y86>
			<x87>145</x87>
			<y87>271.875</y87>
			<x88>145</x88>
			<y88>250.625</y88>
			<x89>143.333333</x89>
			<y89>249.375</y89>
			<x90>143.333333</x90>
			<y90>245.625</y90>
			<x91>140</x91>
			<y91>241.875</y91>
			<x92>140</x92>
			<y92>238.125</y92>
			<x93>137.5</x93>
			<y93>236.25</y93>
			<x94>130.833333</x94>
			<y94>236.25</y94>
			<x95>110.833333</x95>
			<y95>221.25</y95>
			<x96>109.166667</x96>
			<y96>221.25</y96>
			<x97>105.833333</x97>
			<y97>218.75</y97>
			<x98>104.166667</x98>
			<y98>218.75</y98>
			<x99>102.5</x99>
			<y99>216.25</y99>
			<x100>97.5</x100>
			<y100>215</y100>
			<x101>90.833333</x101>
			<y101>210</y101>
			<x102>89.166667</x102>
			<y102>210</y102>
			<x103>86.666667</x103>
			<y103>208.125</y103>
			<x104>85.833333</x104>
			<y104>206.25</y104>
			<x105>80.833333</x105>
			<y105>205</y105>
			<x106>75.833333</x106>
			<y106>201.25</y106>
			<x107>74.166667</x107>
			<y107>201.25</y107>
			<x108>72.5</x108>
			<y108>200</y108>
			<x109>67.5</x109>
			<y109>200</y109>
			<x110>64.166667</x110>
			<y110>197.5</y110>
			<x111>62.5</x111>
			<y111>197.5</y111>
			<x112>57.5</x112>
			<y112>195</y112>
			<x113>49.166667</x113>
			<y113>195</y113>
			<x114>44.166667</x114>
			<y114>192.5</y114>
			<x115>35.833333</x115>
			<y115>192.5</y115>
			<x116>34.166667</x116>
			<y116>191.25</y116>
			<x117>30.833333</x117>
			<y117>191.25</y117>
			<x118>29.166667</x118>
			<y118>190</y118>
			<x119>14.166667</x119>
			<y119>190</y119>
			<x120>10.833333</x120>
			<y120>187.5</y120>
			<x121>0.833333</x121>
			<y121>187.5</y121>
			<x122>0</x122>
			<y122>188.125</y122>
			<x123>0</x123>
			<y123>245.625</y123>
			<x124>3.333333</x124>
			<y124>248.125</y124>
			<x125>0</x125>
			<y125>250.625</y125>
			<x126>0</x126>
			<y126>256.875</y126>
			<x127>1.666667</x127>
			<y127>258.125</y127>
			<x128>1.666667</x128>
			<y128>259.375</y128>
			<x129>0</x129>
			<y129>260.625</y129>
			<x130>0</x130>
			<y130>261.875</y130>
			<x131>1.666667</x131>
			<y131>263.125</y131>
			<x132>0</x132>
			<y132>264.375</y132>
			<x133>0</x133>
			<y133>271.875</y133>
			<x134>1.666667</x134>
			<y134>273.125</y134>
			<x135>1.666667</x135>
			<y135>274.375</y135>
			<x136>0</x136>
			<y136>275.625</y136>
			<x137>0</x137>
			<y137>276.875</y137>
			<x138>1.666667</x138>
			<y138>278.125</y138>
			<x139>1.666667</x139>
			<y139>279.375</y139>
			<x140>0</x140>
			<y140>280.625</y140>
			<x141>0</x141>
			<y141>363.125</y141>
			<x142>1.666667</x142>
			<y142>364.375</y142>
			<x143>0</x143>
			<y143>365.625</y143>
			<x144>0</x144>
			<y144>371.875</y144>
			<x145>1.666667</x145>
			<y145>373.125</y145>
			<x146>1.666667</x146>
			<y146>374.375</y146>
			<x147>0</x147>
			<y147>375.625</y147>
			<x148>0</x148>
			<y148>434.375</y148>
		</polygon>
	</object>
	<object>
		<name>taxi</name>
		<pose>Unspecified</pose>
		<truncated>0</truncated>
		<difficult>0</difficult>
		<occluded>0</occluded>
		<bndbox>
			<xmin>236</xmin>
			<xmax>274</xmax>
			<ymin>152</ymin>
			<ymax>187</ymax>
		</bndbox>
		<polygon>
			<x1>270.833333</x1>
			<y1>181.25</y1>
			<x2>273.333333</x2>
			<y2>179.375</y2>
			<x3>273.333333</x3>
			<y3>161.875</y3>
			<x4>270</x4>
			<y4>159.375</y4>
			<x5>270</x5>
			<y5>158.125</y5>
			<x6>268.333333</x6>
			<y6>156.875</y6>
			<x7>268.333333</x7>
			<y7>154.375</y7>
			<x8>265.833333</x8>
			<y8>153.75</y8>
			<x9>264.166667</x9>
			<y9>152.5</y9>
			<x10>255.833333</x10>
			<y10>152.5</y10>
			<x11>254.166667</x11>
			<y11>151.25</y11>
			<x12>240.833333</x12>
			<y12>151.25</y12>
			<x13>239.166667</x13>
			<y13>152.5</y13>
			<x14>237.5</x14>
			<y14>152.5</y14>
			<x15>235</x15>
			<y15>154.375</y15>
			<x16>236.666667</x16>
			<y16>155.625</y16>
			<x17>236.666667</x17>
			<y17>156.875</y17>
			<x18>241.666667</x18>
			<y18>160.625</y18>
			<x19>241.666667</x19>
			<y19>161.875</y19>
			<x20>243.333333</x20>
			<y20>163.125</y20>
			<x21>243.333333</x21>
			<y21>169.375</y21>
			<x22>246.666667</x22>
			<y22>171.875</y22>
			<x23>246.666667</x23>
			<y23>173.125</y23>
			<x24>248.333333</x24>
			<y24>174.375</y24>
			<x25>248.333333</x25>
			<y25>179.375</y25>
			<x26>252.5</x26>
			<y26>182.5</y26>
			<x27>257.5</x27>
			<y27>182.5</y27>
			<x28>262.5</x28>
			<y28>186.25</y28>
			<x29>265</x29>
			<y29>185.625</y29>
			<x30>266.666667</x30>
			<y30>184.375</y30>
			<x31>266.666667</x31>
			<y31>181.875</y31>
			<x32>267.5</x32>
			<y32>181.25</y32>
			<x33>270.833333</x33>
			<y33>181.25</y33>
		</polygon>
	</object>
	<object>
		<name>taxi</name>
		<pose>Unspecified</pose>
		<truncated>0</truncated>
		<difficult>0</difficult>
		<occluded>0</occluded>
		<bndbox>
			<xmin>336</xmin>
			<xmax>384</xmax>
			<ymin>151</ymin>
			<ymax>190</ymax>
		</bndbox>
		<polygon>
			<x1>383.333333</x1>
			<y1>179.375</y1>
			<x2>383.333333</x2>
			<y2>176.875</y2>
			<x3>381.666667</x3>
			<y3>175.625</y3>
			<x4>381.666667</x4>
			<y4>171.875</y4>
			<x5>383.333333</x5>
			<y5>170.625</y5>
			<x6>383.333333</x6>
			<y6>155.625</y6>
			<x7>379.166667</x7>
			<y7>152.5</y7>
			<x8>377.5</x8>
			<y8>152.5</y8>
			<x9>375.833333</x9>
			<y9>151.25</y9>
			<x10>370.833333</x10>
			<y10>151.25</y10>
			<x11>369.166667</x11>
			<y11>150</y11>
			<x12>349.166667</x12>
			<y12>150</y12>
			<x13>345</x13>
			<y13>153.125</y13>
			<x14>345</x14>
			<y14>154.375</y14>
			<x15>343.333333</x15>
			<y15>155.625</y15>
			<x16>343.333333</x16>
			<y16>156.875</y16>
			<x17>340</x17>
			<y17>160.625</y17>
			<x18>340</x18>
			<y18>164.375</y18>
			<x19>336.666667</x19>
			<y19>168.125</y19>
			<x20>336.666667</x20>
			<y20>176.875</y20>
			<x21>335</x21>
			<y21>178.125</y21>
			<x22>335</x22>
			<y22>181.875</y22>
			<x23>335.833333</x23>
			<y23>182.5</y23>
			<x24>337.5</x24>
			<y24>181.25</y24>
			<x25>340.833333</x25>
			<y25>186.25</y25>
			<x26>342.5</x26>
			<y26>186.25</y26>
			<x27>347.5</x27>
			<y27>182.5</y27>
			<x28>350.833333</x28>
			<y28>182.5</y28>
			<x29>352.5</x29>
			<y29>183.75</y29>
			<x30>364.166667</x30>
			<y30>183.75</y30>
			<x31>369.166667</x31>
			<y31>186.25</y31>
			<x32>372.5</x32>
			<y32>186.25</y32>
			<x33>375.833333</x33>
			<y33>188.75</y33>
			<x34>379.166667</x34>
			<y34>188.75</y34>
			<x35>380</x35>
			<y35>188.125</y35>
			<x36>380</x36>
			<y36>185.625</y36>
			<x37>381.666667</x37>
			<y37>184.375</y37>
			<x38>381.666667</x38>
			<y38>180.625</y38>
			<x39>383.333333</x39>
			<y39>179.375</y39>
		</polygon>
	</object>
	<object>
		<name>taxi</name>
		<pose>Unspecified</pose>
		<truncated>0</truncated>
		<difficult>0</difficult>
		<occluded>0</occluded>
		<bndbox>
			<xmin>401</xmin>
			<xmax>453</xmax>
			<ymin>164</ymin>
			<ymax>191</ymax>
		</bndbox>
		<polygon>
			<x1>451.666667</x1>
			<y1>179.375</y1>
			<x2>450</x2>
			<y2>178.125</y2>
			<x3>450</x3>
			<y3>176.875</y3>
			<x4>446.666667</x4>
			<y4>173.125</y4>
			<x5>446.666667</x5>
			<y5>170.625</y5>
			<x6>445</x6>
			<y6>169.375</y6>
			<x7>445</x7>
			<y7>168.125</y7>
			<x8>437.5</x8>
			<y8>162.5</y8>
			<x9>407.5</x9>
			<y9>162.5</y9>
			<x10>406.666667</x10>
			<y10>164.375</y10>
			<x11>401.666667</x11>
			<y11>168.125</y11>
			<x12>401.666667</x12>
			<y12>169.375</y12>
			<x13>400</x13>
			<y13>170.625</y13>
			<x14>400</x14>
			<y14>184.375</y14>
			<x15>400.833333</x15>
			<y15>185</y15>
			<x16>405.833333</x16>
			<y16>183.75</y16>
			<x17>409.166667</x17>
			<y17>188.75</y17>
			<x18>415.833333</x18>
			<y18>188.75</y18>
			<x19>417.5</x19>
			<y19>187.5</y19>
			<x20>427.5</x20>
			<y20>187.5</y20>
			<x21>429.166667</x21>
			<y21>188.75</y21>
			<x22>432.5</x22>
			<y22>188.75</y22>
			<x23>434.166667</x23>
			<y23>187.5</y23>
			<x24>435.833333</x24>
			<y24>187.5</y24>
			<x25>437.5</x25>
			<y25>188.75</y25>
			<x26>442.5</x26>
			<y26>188.75</y26>
			<x27>444.166667</x27>
			<y27>190</y27>
			<x28>447.5</x28>
			<y28>190</y28>
			<x29>448.333333</x29>
			<y29>189.375</y29>
			<x30>450</x30>
			<y30>188.125</y30>
			<x31>450</x31>
			<y31>185.625</y31>
			<x32>451.666667</x32>
			<y32>184.375</y32>
			<x33>451.666667</x33>
			<y33>179.375</y33>
		</polygon>
	</object>
	<object>
		<name>particulier</name>
		<pose>Unspecified</pose>
		<truncated>0</truncated>
		<difficult>0</difficult>
		<occluded>0</occluded>
		<bndbox>
			<xmin>96</xmin>
			<xmax>244</xmax>
			<ymin>139</ymin>
			<ymax>232</ymax>
		</bndbox>
		<polygon>
			<x1>220</x1>
			<y1>221.875</y1>
			<x2>221.666667</x2>
			<y2>220.625</y2>
			<x3>221.666667</x3>
			<y3>218.125</y3>
			<x4>223.333333</x4>
			<y4>216.875</y4>
			<x5>223.333333</x5>
			<y5>211.875</y5>
			<x6>225.833333</x6>
			<y6>210</y6>
			<x7>227.5</x7>
			<y7>210</y7>
			<x8>229.166667</x8>
			<y8>211.25</y8>
			<x9>237.5</x9>
			<y9>211.25</y9>
			<x10>240</x10>
			<y10>209.375</y10>
			<x11>240</x11>
			<y11>199.375</y11>
			<x12>241.666667</x12>
			<y12>198.125</y12>
			<x13>241.666667</x13>
			<y13>190.625</y13>
			<x14>243.333333</x14>
			<y14>189.375</y14>
			<x15>243.333333</x15>
			<y15>170.625</y15>
			<x16>241.666667</x16>
			<y16>169.375</y16>
			<x17>241.666667</x17>
			<y17>164.375</y17>
			<x18>240</x18>
			<y18>163.125</y18>
			<x19>240</x19>
			<y19>160.625</y19>
			<x20>236.666667</x20>
			<y20>158.125</y20>
			<x21>233.333333</x21>
			<y21>150.625</y21>
			<x22>230.833333</x22>
			<y22>150</y22>
			<x23>228.333333</x23>
			<y23>148.125</y23>
			<x24>228.333333</x24>
			<y24>146.875</y24>
			<x25>224.166667</x25>
			<y25>143.75</y25>
			<x26>222.5</x26>
			<y26>143.75</y26>
			<x27>217.5</x27>
			<y27>141.25</y27>
			<x28>212.5</x28>
			<y28>141.25</y28>
			<x29>210.833333</x29>
			<y29>140</y29>
			<x30>197.5</x30>
			<y30>140</y30>
			<x31>195.833333</x31>
			<y31>138.75</y31>
			<x32>180.833333</x32>
			<y32>138.75</y32>
			<x33>179.166667</x33>
			<y33>137.5</y33>
			<x34>172.5</x34>
			<y34>137.5</y34>
			<x35>170.833333</x35>
			<y35>138.75</y35>
			<x36>150.833333</x36>
			<y36>138.75</y36>
			<x37>149.166667</x37>
			<y37>140</y37>
			<x38>140.833333</x38>
			<y38>140</y38>
			<x39>140</x39>
			<y39>141.875</y39>
			<x40>133.333333</x40>
			<y40>146.875</y40>
			<x41>133.333333</x41>
			<y41>149.375</y41>
			<x42>130.833333</x42>
			<y42>150</y42>
			<x43>128.333333</x43>
			<y43>151.875</y43>
			<x44>128.333333</x44>
			<y44>154.375</y44>
			<x45>121.666667</x45>
			<y45>160.625</y45>
			<x46>120</x46>
			<y46>164.375</y46>
			<x47>117.5</x47>
			<y47>165</y47>
			<x48>112.5</x48>
			<y48>170</y48>
			<x49>109.166667</x49>
			<y49>170</y49>
			<x50>107.5</x50>
			<y50>171.25</y50>
			<x51>104.166667</x51>
			<y51>171.25</y51>
			<x52>96.666667</x52>
			<y52>176.875</y52>
			<x53>96.666667</x53>
			<y53>180.625</y53>
			<x54>95</x54>
			<y54>181.875</y54>
			<x55>95</x55>
			<y55>185.625</y55>
			<x56>96.666667</x56>
			<y56>186.875</y56>
			<x57>96.666667</x57>
			<y57>191.875</y57>
			<x58>100</x58>
			<y58>195.625</y58>
			<x59>100</x59>
			<y59>198.125</y59>
			<x60>102.5</x60>
			<y60>198.75</y60>
			<x61>104.166667</x61>
			<y61>200</y61>
			<x62>105.833333</x62>
			<y62>200</y62>
			<x63>106.666667</x63>
			<y63>201.875</y63>
			<x64>108.333333</x64>
			<y64>203.125</y64>
			<x65>108.333333</x65>
			<y65>204.375</y65>
			<x66>111.666667</x66>
			<y66>205.625</y66>
			<x67>111.666667</x67>
			<y67>206.875</y67>
			<x68>113.333333</x68>
			<y68>208.125</y68>
			<x69>113.333333</x69>
			<y69>210.625</y69>
			<x70>116.666667</x70>
			<y70>214.375</y70>
			<x71>116.666667</x71>
			<y71>218.125</y71>
			<x72>119.166667</x72>
			<y72>220</y72>
			<x73>122.5</x73>
			<y73>220</y73>
			<x74>127.5</x74>
			<y74>215</y74>
			<x75>139.166667</x75>
			<y75>215</y75>
			<x76>140.833333</x76>
			<y76>213.75</y76>
			<x77>149.166667</x77>
			<y77>213.75</y77>
			<x78>150.833333</x78>
			<y78>215</y78>
			<x79>169.166667</x79>
			<y79>215</y79>
			<x80>170.833333</x80>
			<y80>216.25</y80>
			<x81>174.166667</x81>
			<y81>216.25</y81>
			<x82>175.833333</x82>
			<y82>217.5</y82>
			<x83>185.833333</x83>
			<y83>217.5</y83>
			<x84>187.5</x84>
			<y84>218.75</y84>
			<x85>195.833333</x85>
			<y85>218.75</y85>
			<x86>198.333333</x86>
			<y86>220.625</y86>
			<x87>198.333333</x87>
			<y87>223.125</y87>
			<x88>200</x88>
			<y88>224.375</y88>
			<x89>200</x89>
			<y89>228.125</y89>
			<x90>204.166667</x90>
			<y90>231.25</y90>
			<x91>214.166667</x91>
			<y91>231.25</y91>
			<x92>215</x92>
			<y92>230.625</y92>
			<x93>217.5</x93>
			<y93>230</y93>
			<x94>218.333333</x94>
			<y94>228.125</y94>
			<x95>220</x95>
			<y95>226.875</y95>
			<x96>220</x96>
			<y96>221.875</y96>
		</polygon>
	</object>
	<object>
		<name>person</name>
		<pose>Unspecified</pose>
		<truncated>0</truncated>
		<difficult>0</difficult>
		<occluded>0</occluded>
		<bndbox>
			<xmin>284</xmin>
			<xmax>296</xmax>
			<ymin>151</ymin>
			<ymax>179</ymax>
		</bndbox>
		<polygon>
			<x1>295</x1>
			<y1>154.375</y1>
			<x2>293.333333</x2>
			<y2>153.125</y2>
			<x3>293.333333</x3>
			<y3>151.875</y3>
			<x4>290.833333</x4>
			<y4>150</y4>
			<x5>289.166667</x5>
			<y5>150</y5>
			<x6>283.333333</x6>
			<y6>154.375</y6>
			<x7>283.333333</x7>
			<y7>160.625</y7>
			<x8>285</x8>
			<y8>161.875</y8>
			<x9>285</x9>
			<y9>175.625</y9>
			<x10>287.5</x10>
			<y10>177.5</y10>
			<x11>290.833333</x11>
			<y11>177.5</y11>
			<x12>291.666667</x12>
			<y12>176.875</y12>
			<x13>293.333333</x13>
			<y13>175.625</y13>
			<x14>293.333333</x14>
			<y14>164.375</y14>
			<x15>295</x15>
			<y15>163.125</y15>
			<x16>295</x16>
			<y16>154.375</y16>
		</polygon>
	</object>
	<object>
		<name>person</name>
		<pose>Unspecified</pose>
		<truncated>0</truncated>
		<difficult>0</difficult>
		<occluded>0</occluded>
		<bndbox>
			<xmin>303</xmin>
			<xmax>309</xmax>
			<ymin>151</ymin>
			<ymax>169</ymax>
		</bndbox>
		<polygon>
			<x1>306.666667</x1>
			<y1>151.875</y1>
			<x2>305.833333</x2>
			<y2>150</y2>
			<x3>303.333333</x3>
			<y3>151.875</y3>
			<x4>303.333333</x4>
			<y4>153.125</y4>
			<x5>301.666667</x5>
			<y5>154.375</y5>
			<x6>301.666667</x6>
			<y6>159.375</y6>
			<x7>303.333333</x7>
			<y7>160.625</y7>
			<x8>303.333333</x8>
			<y8>166.875</y8>
			<x9>304.166667</x9>
			<y9>167.5</y9>
			<x10>306.666667</x10>
			<y10>166.875</y10>
			<x11>306.666667</x11>
			<y11>163.125</y11>
			<x12>308.333333</x12>
			<y12>161.875</y12>
			<x13>308.333333</x13>
			<y13>153.125</y13>
			<x14>306.666667</x14>
			<y14>151.875</y14>
		</polygon>
	</object>
	<object>
		<name>person</name>
		<pose>Unspecified</pose>
		<truncated>0</truncated>
		<difficult>0</difficult>
		<occluded>0</occluded>
		<bndbox>
			<xmin>389</xmin>
			<xmax>403</xmax>
			<ymin>157</ymin>
			<ymax>186</ymax>
		</bndbox>
		<polygon>
			<x1>396.666667</x1>
			<y1>174.375</y1>
			<x2>398.333333</x2>
			<y2>173.125</y2>
			<x3>398.333333</x3>
			<y3>171.875</y3>
			<x4>401.666667</x4>
			<y4>168.125</y4>
			<x5>401.666667</x5>
			<y5>163.125</y5>
			<x6>398.333333</x6>
			<y6>160.625</y6>
			<x7>398.333333</x7>
			<y7>158.125</y7>
			<x8>395.833333</x8>
			<y8>156.25</y8>
			<x9>393.333333</x9>
			<y9>156.875</y9>
			<x10>393.333333</x10>
			<y10>160.625</y10>
			<x11>390</x11>
			<y11>161.875</y11>
			<x12>390</x12>
			<y12>164.375</y12>
			<x13>388.333333</x13>
			<y13>165.625</y13>
			<x14>388.333333</x14>
			<y14>170.625</y14>
			<x15>390</x15>
			<y15>171.875</y15>
			<x16>390</x16>
			<y16>184.375</y16>
			<x17>390.833333</x17>
			<y17>185</y17>
			<x18>393.333333</x18>
			<y18>184.375</y18>
			<x19>395</x19>
			<y19>183.125</y19>
			<x20>395</x20>
			<y20>180.625</y20>
			<x21>396.666667</x21>
			<y21>179.375</y21>
			<x22>396.666667</x22>
			<y22>174.375</y22>
		</polygon>
	</object>
	<object>
		<name>person</name>
		<pose>Unspecified</pose>
		<truncated>0</truncated>
		<difficult>0</difficult>
		<occluded>0</occluded>
		<bndbox>
			<xmin>454</xmin>
			<xmax>473</xmax>
			<ymin>161</ymin>
			<ymax>194</ymax>
		</bndbox>
		<polygon>
			<x1>463.333333</x1>
			<y1>183.125</y1>
			<x2>464.166667</x2>
			<y2>181.25</y2>
			<x3>466.666667</x3>
			<y3>183.125</y3>
			<x4>466.666667</x4>
			<y4>190.625</y4>
			<x5>467.5</x5>
			<y5>191.25</y5>
			<x6>468.333333</x6>
			<y6>190.625</y6>
			<x7>468.333333</x7>
			<y7>185.625</y7>
			<x8>470</x8>
			<y8>184.375</y8>
			<x9>470</x9>
			<y9>178.125</y9>
			<x10>468.333333</x10>
			<y10>176.875</y10>
			<x11>468.333333</x11>
			<y11>175.625</y11>
			<x12>471.666667</x12>
			<y12>173.125</y12>
			<x13>471.666667</x13>
			<y13>161.875</y13>
			<x14>469.166667</x14>
			<y14>160</y14>
			<x15>465</x15>
			<y15>163.125</y15>
			<x16>463.333333</x16>
			<y16>166.875</y16>
			<x17>460</x17>
			<y17>169.375</y17>
			<x18>460</x18>
			<y18>174.375</y18>
			<x19>458.333333</x19>
			<y19>175.625</y19>
			<x20>458.333333</x20>
			<y20>179.375</y20>
			<x21>460</x21>
			<y21>180.625</y21>
			<x22>460</x22>
			<y22>181.875</y22>
			<x23>456.666667</x23>
			<y23>184.375</y23>
			<x24>456.666667</x24>
			<y24>185.625</y24>
			<x25>453.333333</x25>
			<y25>189.375</y25>
			<x26>453.333333</x26>
			<y26>191.875</y26>
			<x27>454.166667</x27>
			<y27>192.5</y27>
			<x28>457.5</x28>
			<y28>192.5</y28>
			<x29>458.333333</x29>
			<y29>191.875</y29>
			<x30>458.333333</x30>
			<y30>188.125</y30>
			<x31>460</x31>
			<y31>186.875</y31>
			<x32>460</x32>
			<y32>185.625</y32>
			<x33>463.333333</x33>
			<y33>183.125</y33>
		</polygon>
	</object>
	<object>
		<name>person</name>
		<pose>Unspecified</pose>
		<truncated>0</truncated>
		<difficult>0</difficult>
		<occluded>0</occluded>
		<bndbox>
			<xmin>324</xmin>
			<xmax>331</xmax>
			<ymin>150</ymin>
			<ymax>159</ymax>
		</bndbox>
		<polygon>
			<x1>325.833333</x1>
			<y1>148.75</y1>
			<x2>323.333333</x2>
			<y2>150.625</y2>
			<x3>323.333333</x3>
			<y3>155.625</y3>
			<x4>325.833333</x4>
			<y4>157.5</y4>
			<x5>328.333333</x5>
			<y5>156.875</y5>
			<x6>330</x6>
			<y6>155.625</y6>
			<x7>330</x7>
			<y7>150.625</y7>
			<x8>327.5</x8>
			<y8>148.75</y8>
			<x9>325.833333</x9>
			<y9>148.75</y9>
		</polygon>
	</object>
	<object>
		<name>person</name>
		<pose>Unspecified</pose>
		<truncated>0</truncated>
		<difficult>0</difficult>
		<occluded>0</occluded>
		<bndbox>
			<xmin>314</xmin>
			<xmax>321</xmax>
			<ymin>154</ymin>
			<ymax>170</ymax>
		</bndbox>
		<polygon>
			<x1>315.833333</x1>
			<y1>153.75</y1>
			<x2>313.333333</x2>
			<y2>154.375</y2>
			<x3>313.333333</x3>
			<y3>166.875</y3>
			<x4>315.833333</x4>
			<y4>168.75</y4>
			<x5>318.333333</x5>
			<y5>168.125</y5>
			<x6>320</x6>
			<y6>166.875</y6>
			<x7>320</x7>
			<y7>154.375</y7>
			<x8>317.5</x8>
			<y8>152.5</y8>
			<x9>315.833333</x9>
			<y9>153.75</y9>
		</polygon>
	</object>
	<object>
		<name>person</name>
		<pose>Unspecified</pose>
		<truncated>0</truncated>
		<difficult>0</difficult>
		<occluded>0</occluded>
		<bndbox>
			<xmin>331</xmin>
			<xmax>341</xmax>
			<ymin>152</ymin>
			<ymax>165</ymax>
		</bndbox>
		<polygon>
			<x1>338.333333</x1>
			<y1>153.125</y1>
			<x2>335.833333</x2>
			<y2>151.25</y2>
			<x3>334.166667</x3>
			<y3>151.25</y3>
			<x4>333.333333</x4>
			<y4>153.125</y4>
			<x5>331.666667</x5>
			<y5>154.375</y5>
			<x6>331.666667</x6>
			<y6>155.625</y6>
			<x7>330</x7>
			<y7>156.875</y7>
			<x8>330</x8>
			<y8>161.875</y8>
			<x9>332.5</x9>
			<y9>163.75</y9>
			<x10>335.833333</x10>
			<y10>163.75</y10>
			<x11>336.666667</x11>
			<y11>163.125</y11>
			<x12>338.333333</x12>
			<y12>161.875</y12>
			<x13>340</x13>
			<y13>158.125</y13>
			<x14>338.333333</x14>
			<y14>156.875</y14>
			<x15>338.333333</x15>
			<y15>153.125</y15>
		</polygon>
	</object>
	<object>
		<name>camion</name>
		<pose>Unspecified</pose>
		<truncated>0</truncated>
		<difficult>0</difficult>
		<occluded>0</occluded>
		<bndbox>
			<xmin>271</xmin>
			<xmax>296</xmax>
			<ymin>139</ymin>
			<ymax>152</ymax>
		</bndbox>
		<polygon>
			<x1>295</x1>
			<y1>146.875</y1>
			<x2>295</x2>
			<y2>139.375</y2>
			<x3>292.5</x3>
			<y3>137.5</y3>
			<x4>270.833333</x4>
			<y4>137.5</y4>
			<x5>270</x5>
			<y5>138.125</y5>
			<x6>270</x6>
			<y6>148.125</y6>
			<x7>270.833333</x7>
			<y7>148.75</y7>
			<x8>275.833333</x8>
			<y8>148.75</y8>
			<x9>277.5</x9>
			<y9>150</y9>
			<x10>280.833333</x10>
			<y10>150</y10>
			<x11>282.5</x11>
			<y11>151.25</y11>
			<x12>287.5</x12>
			<y12>151.25</y12>
			<x13>288.333333</x13>
			<y13>150.625</y13>
			<x14>289.166667</x14>
			<y14>150</y14>
			<x15>292.5</x15>
			<y15>150</y15>
			<x16>293.333333</x16>
			<y16>148.125</y16>
			<x17>295</x17>
			<y17>146.875</y17>
		</polygon>
	</object>
	<object>
		<name>car rapide</name>
		<pose>Unspecified</pose>
		<truncated>0</truncated>
		<difficult>0</difficult>
		<occluded>0</occluded>
		<bndbox>
			<xmin>324</xmin>
			<xmax>349</xmax>
			<ymin>145</ymin>
			<ymax>157</ymax>
		</bndbox>
		<polygon>
			<x1>346.666667</x1>
			<y1>150.625</y1>
			<x2>348.333333</x2>
			<y2>149.375</y2>
			<x3>348.333333</x3>
			<y3>148.125</y3>
			<x4>346.666667</x4>
			<y4>146.875</y4>
			<x5>345.833333</x5>
			<y5>145</y5>
			<x6>340.833333</x6>
			<y6>145</y6>
			<x7>339.166667</x7>
			<y7>143.75</y7>
			<x8>327.5</x8>
			<y8>143.75</y8>
			<x9>323.333333</x9>
			<y9>146.875</y9>
			<x10>324.166667</x10>
			<y10>148.75</y10>
			<x11>327.5</x11>
			<y11>148.75</y11>
			<x12>330</x12>
			<y12>150.625</y12>
			<x13>330</x13>
			<y13>154.375</y13>
			<x14>330.833333</x14>
			<y14>155</y14>
			<x15>334.166667</x15>
			<y15>152.5</y15>
			<x16>335.833333</x16>
			<y16>152.5</y16>
			<x17>336.666667</x17>
			<y17>154.375</y17>
			<x18>339.166667</x18>
			<y18>156.25</y18>
			<x19>341.666667</x19>
			<y19>155.625</y19>
			<x20>343.333333</x20>
			<y20>154.375</y20>
			<x21>343.333333</x21>
			<y21>153.125</y21>
			<x22>345.833333</x22>
			<y22>152.5</y22>
			<x23>346.666667</x23>
			<y23>150.625</y23>
		</polygon>
	</object>
</annotation>
