<annotation>
	<folder></folder>
	<filename>IMG_20231107_122916_404_jpg.rf.5c0bd456849956b83b4009ea2a78782f.jpg</filename>
	<path>IMG_20231107_122916_404_jpg.rf.5c0bd456849956b83b4009ea2a78782f.jpg</path>
	<source>
		<database>roboflow.com</database>
	</source>
	<size>
		<width>640</width>
		<height>640</height>
		<depth>3</depth>
	</size>
	<segmented>0</segmented>
	<object>
		<name>moto</name>
		<pose>Unspecified</pose>
		<truncated>0</truncated>
		<difficult>0</difficult>
		<occluded>0</occluded>
		<bndbox>
			<xmin>121</xmin>
			<xmax>136</xmax>
			<ymin>198</ymin>
			<ymax>210</ymax>
		</bndbox>
		<polygon>
			<x1>130.833333</x1>
			<y1>209.440032</y1>
			<x2>135</x2>
			<y2>207.565032</y2>
			<x3>133.333333</x3>
			<y3>202.565032</y3>
			<x4>129.166667</x4>
			<y4>198.190032</y4>
			<x5>125.833333</x5>
			<y5>196.940032</y5>
			<x6>121.666667</x6>
			<y6>198.815032</y6>
			<x7>120</x7>
			<y7>201.315032</y7>
			<x8>120</x8>
			<y8>206.315032</y8>
			<x9>122.5</x9>
			<y9>208.190032</y9>
			<x10>130.833333</x10>
			<y10>209.440032</y10>
		</polygon>
	</object>
	<object>
		<name>taxi</name>
		<pose>Unspecified</pose>
		<truncated>0</truncated>
		<difficult>0</difficult>
		<occluded>0</occluded>
		<bndbox>
			<xmin>281</xmin>
			<xmax>383</xmax>
			<ymin>196</ymin>
			<ymax>220</ymax>
		</bndbox>
		<polygon>
			<x1>377.5</x1>
			<y1>218.75</y1>
			<x2>380</x2>
			<y2>216.875</y2>
			<x3>381.666667</x3>
			<y3>213.125</y3>
			<x4>380</x4>
			<y4>205.625</y4>
			<x5>377.5</x5>
			<y5>202.5</y5>
			<x6>350.833333</x6>
			<y6>195</y6>
			<x7>320.833333</x7>
			<y7>195</y7>
			<x8>312.5</x8>
			<y8>196.25</y8>
			<x9>284.166667</x9>
			<y9>207.5</y9>
			<x10>280</x10>
			<y10>210.625</y10>
			<x11>280</x11>
			<y11>214.375</y11>
			<x12>282.5</x12>
			<y12>216.25</y12>
			<x13>377.5</x13>
			<y13>218.75</y13>
		</polygon>
	</object>
	<object>
		<name>taxi</name>
		<pose>Unspecified</pose>
		<truncated>0</truncated>
		<difficult>0</difficult>
		<occluded>0</occluded>
		<bndbox>
			<xmin>373</xmin>
			<xmax>414</xmax>
			<ymin>190</ymin>
			<ymax>201</ymax>
		</bndbox>
		<polygon>
			<x1>413.333333</x1>
			<y1>195.625</y1>
			<x2>409.166667</x2>
			<y2>191.25</y2>
			<x3>400.833333</x3>
			<y3>188.75</y3>
			<x4>387.5</x4>
			<y4>188.75</y4>
			<x5>372.5</x5>
			<y5>193.75</y5>
			<x6>371.666667</x6>
			<y6>198.125</y6>
			<x7>374.166667</x7>
			<y7>200</y7>
			<x8>407.5</x8>
			<y8>200</y8>
			<x9>413.333333</x9>
			<y9>195.625</y9>
		</polygon>
	</object>
	<object>
		<name>taxi</name>
		<pose>Unspecified</pose>
		<truncated>0</truncated>
		<difficult>0</difficult>
		<occluded>0</occluded>
		<bndbox>
			<xmin>1</xmin>
			<xmax>38</xmax>
			<ymin>204</ymin>
			<ymax>231</ymax>
		</bndbox>
		<polygon>
			<x1>0</x1>
			<y1>228.125</y1>
			<x2>34.166667</x2>
			<y2>230</y2>
			<x3>36.666667</x3>
			<y3>224.375</y3>
			<x4>36.666667</x4>
			<y4>220.625</y4>
			<x5>31.666667</x5>
			<y5>211.875</y5>
			<x6>15.833333</x6>
			<y6>203.75</y6>
			<x7>9.166667</x7>
			<y7>202.5</y7>
			<x8>2.5</x8>
			<y8>202.5</y8>
			<x9>0</x9>
			<y9>204.375</y9>
			<x10>0</x10>
			<y10>228.125</y10>
		</polygon>
	</object>
	<object>
		<name>camion</name>
		<pose>Unspecified</pose>
		<truncated>0</truncated>
		<difficult>0</difficult>
		<occluded>0</occluded>
		<bndbox>
			<xmin>11</xmin>
			<xmax>78</xmax>
			<ymin>177</ymin>
			<ymax>208</ymax>
		</bndbox>
		<polygon>
			<x1>15.833333</x1>
			<y1>202.5</y1>
			<x2>20.833333</x2>
			<y2>205</y2>
			<x3>37.5</x3>
			<y3>206.25</y3>
			<x4>74.828942</x4>
			<y4>206.707375</y4>
			<x5>76.926597</x5>
			<y5>186.365584</y5>
			<x6>74.572594</x6>
			<y6>177.655807</y6>
			<x7>30.833333</x7>
			<y7>176.25</y7>
			<x8>13.333333</x8>
			<y8>178.125</y8>
			<x9>10</x9>
			<y9>181.875</y9>
			<x10>10</x10>
			<y10>190.625</y10>
			<x11>13.333333</x11>
			<y11>200.625</y11>
			<x12>15.833333</x12>
			<y12>202.5</y12>
		</polygon>
	</object>
	<object>
		<name>particulier</name>
		<pose>Unspecified</pose>
		<truncated>0</truncated>
		<difficult>0</difficult>
		<occluded>0</occluded>
		<bndbox>
			<xmin>228</xmin>
			<xmax>259</xmax>
			<ymin>191</ymin>
			<ymax>199</ymax>
		</bndbox>
		<polygon>
			<x1>258.333333</x1>
			<y1>195.625</y1>
			<x2>255</x2>
			<y2>191.875</y2>
			<x3>250.833333</x3>
			<y3>190</y3>
			<x4>237.5</x4>
			<y4>190</y4>
			<x5>229.166667</x5>
			<y5>193.75</y5>
			<x6>226.666667</x6>
			<y6>195.625</y6>
			<x7>227.5</x7>
			<y7>197.5</y7>
			<x8>255.833333</x8>
			<y8>197.5</y8>
			<x9>258.333333</x9>
			<y9>195.625</y9>
		</polygon>
	</object>
	<object>
		<name>particulier</name>
		<pose>Unspecified</pose>
		<truncated>0</truncated>
		<difficult>0</difficult>
		<occluded>0</occluded>
		<bndbox>
			<xmin>311</xmin>
			<xmax>344</xmax>
			<ymin>187</ymin>
			<ymax>197</ymax>
		</bndbox>
		<polygon>
			<x1>340.833333</x1>
			<y1>195</y1>
			<x2>343.333333</x2>
			<y2>193.125</y2>
			<x3>343.333333</x3>
			<y3>191.875</y3>
			<x4>334.166667</x4>
			<y4>186.25</y4>
			<x5>315.833333</x5>
			<y5>186.25</y5>
			<x6>310</x6>
			<y6>190.625</y6>
			<x7>310</x7>
			<y7>194.375</y7>
			<x8>312.5</x8>
			<y8>196.25</y8>
			<x9>340.833333</x9>
			<y9>195</y9>
		</polygon>
	</object>
	<object>
		<name>particulier</name>
		<pose>Unspecified</pose>
		<truncated>0</truncated>
		<difficult>0</difficult>
		<occluded>0</occluded>
		<bndbox>
			<xmin>256</xmin>
			<xmax>278</xmax>
			<ymin>190</ymin>
			<ymax>199</ymax>
		</bndbox>
		<polygon>
			<x1>274.166667</x1>
			<y1>196.25</y1>
			<x2>276.666667</x2>
			<y2>194.375</y2>
			<x3>276.666667</x3>
			<y3>190.625</y3>
			<x4>272.5</x4>
			<y4>188.75</y4>
			<x5>257.5</x5>
			<y5>188.75</y5>
			<x6>255</x6>
			<y6>190.625</y6>
			<x7>255</x7>
			<y7>195.625</y7>
			<x8>259.166667</x8>
			<y8>197.5</y8>
			<x9>274.166667</x9>
			<y9>196.25</y9>
		</polygon>
	</object>
	<object>
		<name>moto tricycle</name>
		<pose>Unspecified</pose>
		<truncated>0</truncated>
		<difficult>0</difficult>
		<occluded>0</occluded>
		<bndbox>
			<xmin>574</xmin>
			<xmax>626</xmax>
			<ymin>179</ymin>
			<ymax>201</ymax>
		</bndbox>
		<polygon>
			<x1>614.166667</x1>
			<y1>200</y1>
			<x2>625</x2>
			<y2>193.125</y2>
			<x3>625</x3>
			<y3>183.125</y3>
			<x4>623.333333</x4>
			<y4>179.375</y4>
			<x5>620.833333</x5>
			<y5>177.5</y5>
			<x6>595.833333</x6>
			<y6>177.5</y6>
			<x7>592.5</x7>
			<y7>178.75</y7>
			<x8>580</x8>
			<y8>189.375</y8>
			<x9>573.333333</x9>
			<y9>196.875</y9>
			<x10>573.333333</x10>
			<y10>198.125</y10>
			<x11>575.833333</x11>
			<y11>200</y11>
			<x12>614.166667</x12>
			<y12>200</y12>
		</polygon>
	</object>
</annotation>
